{
    "name": "Passat Berlina",
    "year": "2015",
    "url": "https://www.km77.com/coches/volkswagen/passat/2015/berlina",
    "price": "Desde 41.200 €",
    "versions": [
        {
            "name": "Passat Edition 1.4 TSI BMT 125 CV",
            "start_year": "2014",
            "end_year": "2018",
            "url": "https://www.km77.com/coches/volkswagen/passat/2015/berlina/edition/passat-edition-14-tsi-bmt-125-cv/datos",
            "price": "25.275",
            "potencia": "125",
            "consumo": "5,3",
            "longitud": "4.767",
            "maletero": "586",
            "specs": [
                {},
                {},
                {},
                {},
                {},
                {},
                {},
                {},
                {},
                {},
                {},
                {},
                {},
                {},
                {}
            ]
        },
        {
            "name": "Passat Edition 1.6 TDI BMT 88 kW (120 CV)",
            "start_year": "2014",
            "end_year": "2019",
            "url": "https://www.km77.com/coches/volkswagen/passat/2015/berlina/edition/passat-edition-16-tdi-bmt-120-cv/datos",
            "price": "27.830",
            "potencia": "120",
            "consumo": "4",
            "longitud": "4.767",
            "maletero": "586",
            "specs": [
                {},
                {},
                {},
                {},
                {},
                {},
                {},
                {},
                {},
                {},
                {},
                {},
                {},
                {},
                {}
            ]
        },
        {
            "name": "Passat BlueMotion 1.6 TDI BMT 120 CV",
            "start_year": "2015",
            "end_year": "2017",
            "url": "https://www.km77.com/coches/volkswagen/passat/2015/berlina/bluemotion/passat-bluemotion-16-tdi-bmt-120-cv/datos",
            "price": "28.170",
            "potencia": "120",
            "consumo": "3,7",
            "longitud": "4.767",
            "maletero": "586",
            "specs": [
                {},
                {},
                {},
                {},
                {},
                {},
                {},
                {},
                {},
                {},
                {},
                {},
                {},
                {},
                {}
            ]
        },
        {
            "name": "Passat Advance 1.4 TSI ACT BMT 110 kW (150 CV)",
            "start_year": "2014",
            "end_year": "2019",
            "url": "https://www.km77.com/coches/volkswagen/passat/2015/berlina/advance/passat-advance-14-tsi-act-bmt-150-cv/datos",
            "price": "29.740",
            "potencia": "150",
            "consumo": "4,9",
            "longitud": "4.767",
            "maletero": "586",
            "specs": [
                {},
                {},
                {},
                {},
                {},
                {},
                {},
                {},
                {},
                {},
                {},
                {},
                {},
                {},
                {}
            ]
        },
        {
            "name": "Passat Advance 1.4 TSI ACT BMT 110 kW (150 CV)",
            "start_year": "2019",
            "end_year": "2019",
            "url": "https://www.km77.com/coches/volkswagen/passat/2015/berlina/advance/passat-advance-14-tsi-act-bmt-110-kw-150-cv/datos",
            "price": "29.820",
            "potencia": "150",
            "consumo": "5,3",
            "longitud": "4.767",
            "maletero": "586",
            "specs": [
                {},
                {},
                {},
                {},
                {},
                {},
                {},
                {},
                {},
                {},
                {},
                {},
                {},
                {},
                {}
            ]
        },
        {
            "name": "Passat Edition 1.6 TDI BMT 88 kW (120 CV) DSG 7 vel.",
            "start_year": "2019",
            "end_year": "2019",
            "url": "https://www.km77.com/coches/volkswagen/passat/2015/berlina/edition/passat-edition-16-tdi-bmt-88-kw-120-cv-dsg-7-vel/datos",
            "price": "30.415",
            "potencia": "120",
            "consumo": "4",
            "longitud": "4.767",
            "maletero": "586",
            "specs": [
                {},
                {},
                {},
                {},
                {},
                {},
                {},
                {},
                {},
                {},
                {},
                {},
                {},
                {},
                {}
            ]
        },
        {
            "name": "Passat Edition 2.0 TDI BMT 110 kW (150 CV)",
            "start_year": "2014",
            "end_year": "2019",
            "url": "https://www.km77.com/coches/volkswagen/passat/2015/berlina/edition/passat-14-tdi-bmt-150-cv/datos",
            "price": "30.495",
            "potencia": "150",
            "consumo": "4,1",
            "longitud": "4.767",
            "maletero": "586",
            "specs": [
                {},
                {},
                {},
                {},
                {},
                {},
                {},
                {},
                {},
                {},
                {},
                {},
                {},
                {},
                {}
            ]
        },
        {
            "name": "Passat Advance 1.6 TDI BMT 88 kW (120 CV)",
            "start_year": "2014",
            "end_year": "2019",
            "url": "https://www.km77.com/coches/volkswagen/passat/2015/berlina/advance/passat-advance-16-tdi-bmt-120-cv/datos",
            "price": "30.855",
            "potencia": "120",
            "consumo": "4",
            "longitud": "4.767",
            "maletero": "586",
            "specs": [
                {},
                {},
                {},
                {},
                {},
                {},
                {},
                {},
                {},
                {},
                {},
                {},
                {},
                {},
                {}
            ]
        },
        {
            "name": "Passat Sport 1.4 TSI ACT BMT 110 kW (150 CV)",
            "start_year": "2014",
            "end_year": "2019",
            "url": "https://www.km77.com/coches/volkswagen/passat/2015/berlina/sport/passat-sport-14-tsi-act-bmt-150-cv/datos",
            "price": "30.990",
            "potencia": "150",
            "consumo": "5",
            "longitud": "4.767",
            "maletero": "586",
            "specs": [
                {},
                {},
                {},
                {},
                {},
                {},
                {},
                {},
                {},
                {},
                {},
                {},
                {},
                {},
                {}
            ]
        },
        {
            "name": "Passat Sport 1.4 TSI ACT BMT 110 kW (150 CV)",
            "start_year": "2014",
            "end_year": "2019",
            "url": "https://www.km77.com/coches/volkswagen/passat/2015/berlina/sport/passat-sport-14-tsi-act-bmt-110-kw-150-cv/datos",
            "price": "31.315",
            "potencia": "150",
            "consumo": "5,3",
            "longitud": "4.767",
            "maletero": "586",
            "specs": [
                {},
                {},
                {},
                {},
                {},
                {},
                {},
                {},
                {},
                {},
                {},
                {},
                {},
                {},
                {}
            ]
        },
        {
            "name": "Passat R-Line 2.0 TDI BMT 150 CV",
            "start_year": "2014",
            "end_year": "2018",
            "url": "https://www.km77.com/coches/volkswagen/passat/2015/berlina/r-line/passat-r-line-20-tdi-bmt-150-cv/datos",
            "price": "32.840",
            "potencia": "150",
            "consumo": "4,2",
            "longitud": "4.767",
            "maletero": "586",
            "specs": [
                {},
                {},
                {},
                {},
                {},
                {},
                {},
                {},
                {},
                {},
                {},
                {},
                {},
                {},
                {},
                {}
            ]
        },
        {
            "name": "Passat Sport 1.8 TSI BMT 180 CV DSG7",
            "start_year": "2015",
            "end_year": "2018",
            "url": "https://www.km77.com/coches/volkswagen/passat/2015/berlina/sport/passat-sport-18-tsi-bmt-180-cv-dsg7/datos",
            "price": "33.180",
            "potencia": "179",
            "consumo": "5,8",
            "longitud": "4.767",
            "maletero": "586",
            "specs": [
                {},
                {},
                {},
                {},
                {},
                {},
                {},
                {},
                {},
                {},
                {},
                {},
                {},
                {},
                {}
            ]
        },
        {
            "name": "Passat Advance 2.0 TDI BMT 150 CV DSG6",
            "start_year": "2014",
            "end_year": "2018",
            "url": "https://www.km77.com/coches/volkswagen/passat/2015/berlina/advance/passat-14-tdi-bmt-150-cv-dsg6/datos",
            "price": "33.260",
            "potencia": "150",
            "consumo": "4,5",
            "longitud": "4.767",
            "maletero": "586",
            "specs": [
                {},
                {},
                {},
                {},
                {},
                {},
                {},
                {},
                {},
                {},
                {},
                {},
                {},
                {},
                {}
            ]
        },
        {
            "name": "Passat Advance 2.0 TDI BMT 110 kW (150 CV)",
            "start_year": "2014",
            "end_year": "2019",
            "url": "https://www.km77.com/coches/volkswagen/passat/2015/berlina/advance/passat-advance-20-tdi-bmt-150-cv/datos",
            "price": "33.610",
            "potencia": "150",
            "consumo": "4,1",
            "longitud": "4.767",
            "maletero": "586",
            "specs": [
                {},
                {},
                {},
                {},
                {},
                {},
                {},
                {},
                {},
                {},
                {},
                {},
                {},
                {},
                {}
            ]
        },
        {
            "name": "Passat R-Line 2.0 TDI BMT 150 CV DSG6",
            "start_year": "2017",
            "end_year": "2018",
            "url": "https://www.km77.com/coches/volkswagen/passat/2015/berlina/r-line/passat-r-line-20-tdi-bmt-150-cv-dsg6/datos",
            "price": "33.840",
            "potencia": "150",
            "consumo": "4,5",
            "longitud": "4.767",
            "maletero": "586",
            "specs": [
                {},
                {},
                {},
                {},
                {},
                {},
                {},
                {},
                {},
                {},
                {},
                {},
                {},
                {},
                {},
                {}
            ]
        },
        {
            "name": "Passat R-Line Exclusive 2.0 TDI BMT 110 (150 CV)",
            "start_year": "2018",
            "end_year": "2019",
            "url": "https://www.km77.com/coches/volkswagen/passat/2015/berlina/r-line-exclusive/passat-r-line-exclusive-20-tdi-bmt-110-150-cv/datos",
            "price": "34.015",
            "potencia": "150",
            "consumo": "4,1",
            "longitud": "4.767",
            "maletero": "586",
            "specs": [
                {},
                {},
                {},
                {},
                {},
                {},
                {},
                {},
                {},
                {},
                {},
                {},
                {},
                {},
                {},
                {}
            ]
        },
        {
            "name": "Passat Sport 2.0 TDI BMT 150 CV DSG6",
            "start_year": "2017",
            "end_year": "2018",
            "url": "https://www.km77.com/coches/volkswagen/passat/2015/berlina/sport/passat-sport-20-tdi-bmt-150-cv-dsg62/datos",
            "price": "34.240",
            "potencia": "150",
            "consumo": "4,6",
            "longitud": "4.767",
            "maletero": "586",
            "specs": [
                {},
                {},
                {},
                {},
                {},
                {},
                {},
                {},
                {},
                {},
                {},
                {},
                {},
                {},
                {}
            ]
        },
        {
            "name": "Passat Sport 2.0 TDI BMT 150 CV DSG6",
            "start_year": "2014",
            "end_year": "2017",
            "url": "https://www.km77.com/coches/volkswagen/passat/2015/berlina/sport/passat-sport-20-tdi-bmt-150-cv-dsg6/datos",
            "price": "34.240",
            "potencia": "150",
            "consumo": "4,5",
            "longitud": "4.767",
            "maletero": "586",
            "specs": [
                {},
                {},
                {},
                {},
                {},
                {},
                {},
                {}
            ]
        },
        {
            "name": "Passat Sport 1.4 TSI ACT BMT 150 CV 4Motion",
            "start_year": "2015",
            "end_year": "2017",
            "url": "https://www.km77.com/coches/volkswagen/passat/2015/berlina/sport/passat-sport-14-tsi-act-bmt-4motion-150-cv/datos",
            "price": "34.635",
            "potencia": "150",
            "consumo": "5,6",
            "longitud": "4.767",
            "maletero": "586",
            "specs": [
                {},
                {},
                {},
                {},
                {},
                {},
                {},
                {},
                {},
                {},
                {},
                {},
                {},
                {},
                {}
            ]
        },
        {
            "name": "Passat Advance 2.0 TDI BMT 110 kW (150 CV) DSG 7 vel.",
            "start_year": "2018",
            "end_year": "2019",
            "url": "https://www.km77.com/coches/volkswagen/passat/2015/berlina/advance/passat-advance-20-tdi-bmt-110-kw-150-cv-dsg-7-vel/datos",
            "price": "34.665",
            "potencia": "150",
            "consumo": "4,2",
            "longitud": "4.767",
            "maletero": "586",
            "specs": [
                {},
                {},
                {},
                {},
                {},
                {},
                {},
                {},
                {},
                {},
                {},
                {},
                {},
                {},
                {}
            ]
        },
        {
            "name": "Passat R-Line Exclusive 2.0 TDI BMT 110 kW (150 CV) DSG 7 vel.",
            "start_year": "2018",
            "end_year": "2019",
            "url": "https://www.km77.com/coches/volkswagen/passat/2015/berlina/r-line-exclusive/passat-r-line-exclusive-20-tdi-bmt-110-kw-150-cv-dsg-7-vel/datos",
            "price": "35.090",
            "potencia": "150",
            "consumo": "4,2",
            "longitud": "4.767",
            "maletero": "586",
            "specs": [
                {},
                {},
                {},
                {},
                {},
                {},
                {},
                {},
                {},
                {},
                {},
                {},
                {},
                {},
                {},
                {}
            ]
        },
        {
            "name": "Passat Sport 2.0 TDI BMT 110 kW (150 CV)",
            "start_year": "2014",
            "end_year": "2019",
            "url": "https://www.km77.com/coches/volkswagen/passat/2015/berlina/sport/passat-sport-20-tdi-bmt-150-cv/datos",
            "price": "35.115",
            "potencia": "150",
            "consumo": "4,2",
            "longitud": "4.767",
            "maletero": "586",
            "specs": [
                {},
                {},
                {},
                {},
                {},
                {},
                {},
                {},
                {},
                {},
                {},
                {},
                {},
                {},
                {}
            ]
        },
        {
            "name": "Passat Advance 1.6 TDI BMT 88 kW (120 CV) DSG 7 vel.",
            "start_year": "2019",
            "end_year": "2019",
            "url": "https://www.km77.com/coches/volkswagen/passat/2015/berlina/advance/passat-advance-16-tdi-bmt-88-kw-120-cv-dsg-7-vel/datos",
            "price": "35.545",
            "potencia": "120",
            "consumo": "4",
            "longitud": "4.767",
            "maletero": "586",
            "specs": [
                {},
                {},
                {},
                {},
                {},
                {},
                {},
                {},
                {},
                {},
                {},
                {},
                {},
                {},
                {}
            ]
        },
        {
            "name": "Passat Advance 2.0 TDI BMT 150 CV 4Motion",
            "start_year": "2015",
            "end_year": "2017",
            "url": "https://www.km77.com/coches/volkswagen/passat/2015/berlina/advance/passat-advance-20-tdi-bmt-4motion-150-cv/datos",
            "price": "35.760",
            "potencia": "150",
            "consumo": "4,5",
            "longitud": "4.767",
            "maletero": "586",
            "specs": [
                {},
                {},
                {},
                {},
                {},
                {},
                {},
                {},
                {},
                {},
                {},
                {},
                {},
                {},
                {}
            ]
        },
        {
            "name": "Passat Sport 2.0 TDI BMT 190 CV DSG6",
            "start_year": "2015",
            "end_year": "2018",
            "url": "https://www.km77.com/coches/volkswagen/passat/2015/berlina/sport/passat-sport-20-tdi-bmt-190-cv-dsg6/datos",
            "price": "35.765",
            "potencia": "190",
            "consumo": "4,6",
            "longitud": "4.767",
            "maletero": "586",
            "specs": [
                {},
                {},
                {},
                {},
                {},
                {},
                {},
                {},
                {},
                {},
                {},
                {},
                {},
                {},
                {}
            ]
        },
        {
            "name": "Passat Sport 2.0 TDI BMT 110 kW (150 CV) DSG 7 vel.",
            "start_year": "2018",
            "end_year": "2019",
            "url": "https://www.km77.com/coches/volkswagen/passat/2015/berlina/sport/passat-sport-20-tdi-bmt-110-kw-150-cv-dsg-7-vel/datos",
            "price": "36.345",
            "potencia": "150",
            "consumo": "4,4",
            "longitud": "4.767",
            "maletero": "586",
            "specs": [
                {},
                {},
                {},
                {},
                {},
                {},
                {},
                {},
                {},
                {},
                {},
                {},
                {},
                {},
                {}
            ]
        },
        {
            "name": "Passat Sport 2.0 TDI BMT 140 kW (190 CV) DSG 7 vel.",
            "start_year": "2019",
            "end_year": "2019",
            "url": "https://www.km77.com/coches/volkswagen/passat/2015/berlina/sport/passat-sport-20-tdi-bmt-140-kw-190-cv-dsg-7-vel/datos",
            "price": "37.760",
            "potencia": "190",
            "consumo": "4,5",
            "longitud": "4.767",
            "maletero": "586",
            "specs": [
                {},
                {},
                {},
                {},
                {},
                {},
                {},
                {},
                {},
                {},
                {},
                {},
                {},
                {},
                {}
            ]
        },
        {
            "name": "Passat Sport 2.0 TDI BMT 150 CV 4Motion",
            "start_year": "2015",
            "end_year": "2017",
            "url": "https://www.km77.com/coches/volkswagen/passat/2015/berlina/sport/passat-sport-20-tdi-bmt-4motion-150-cv/datos",
            "price": "38.030",
            "potencia": "150",
            "consumo": "4,6",
            "longitud": "4.767",
            "maletero": "586",
            "specs": [
                {},
                {},
                {},
                {},
                {},
                {},
                {},
                {},
                {},
                {},
                {},
                {},
                {},
                {},
                {}
            ]
        },
        {
            "name": "Passat Sport 2.0 TSI BMT 220 CV DSG6",
            "start_year": "2015",
            "end_year": "2017",
            "url": "https://www.km77.com/coches/volkswagen/passat/2015/berlina/sport/passat-sport-20-tsi-bmt-220-cv-dsg6/datos",
            "price": "39.915",
            "potencia": "220",
            "consumo": "6,2",
            "longitud": "4.767",
            "maletero": "586",
            "specs": [
                {},
                {},
                {},
                {},
                {},
                {},
                {},
                {},
                {},
                {},
                {},
                {},
                {},
                {},
                {}
            ]
        },
        {
            "name": "Passat Sport 2.0 TDI BMT 190 CV 4Motion DSG6",
            "start_year": "2015",
            "end_year": "2017",
            "url": "https://www.km77.com/coches/volkswagen/passat/2015/berlina/sport/passat-sport-20-tdi-bmt-190-cv-4motion-dsg6/datos",
            "price": "41.525",
            "potencia": "190",
            "consumo": "5",
            "longitud": "4.767",
            "maletero": "586",
            "specs": [
                {},
                {},
                {},
                {},
                {},
                {},
                {},
                {},
                {},
                {},
                {},
                {},
                {},
                {},
                {}
            ]
        },
        {
            "name": "Passat Sport 2.0 TSI BMT 280 CV 4Motion DSG6",
            "start_year": "2015",
            "end_year": "2018",
            "url": "https://www.km77.com/coches/volkswagen/passat/2015/berlina/sport/passat-sport-20-tsi-bmt-280-cv-4motion-dsg6/datos",
            "price": "42.400",
            "potencia": "280",
            "consumo": "7,2",
            "longitud": "4.767",
            "maletero": "586",
            "specs": [
                {},
                {},
                {},
                {},
                {},
                {},
                {},
                {},
                {},
                {},
                {},
                {},
                {},
                {},
                {}
            ]
        },
        {
            "name": "Passat Sport 2.0 TDI BiT BMT 240 CV 4Motion DSG7",
            "start_year": "2016",
            "end_year": "2018",
            "url": "https://www.km77.com/coches/volkswagen/passat/2015/berlina/sport/passat-sport-20-tdi-bit-bmt-240-cv-4motion-dsg7/datos",
            "price": "42.775",
            "potencia": "239",
            "consumo": "5,7",
            "longitud": "4.767",
            "maletero": "586",
            "specs": [
                {},
                {},
                {},
                {},
                {},
                {},
                {},
                {},
                {},
                {},
                {},
                {},
                {},
                {},
                {}
            ]
        },
        {
            "name": "Passat GTE 1.4 TSI ePower DSG 6 vel.",
            "start_year": "2016",
            "end_year": "2019",
            "url": "https://www.km77.com/coches/volkswagen/passat/2015/berlina/gte/passat-gte/datos",
            "price": "44.895",
            "potencia": "218",
            "consumo": "1,8",
            "longitud": "4.767",
            "maletero": "402",
            "specs": [
                {},
                {},
                {},
                {},
                {},
                {},
                {},
                {},
                {},
                {},
                {},
                {},
                {},
                {},
                {},
                {},
                {},
                {}
            ]
        },
        {
            "name": "Passat Sport 2.0 TDI BiT BMT 240 CV 4Motion DSG7",
            "start_year": "2014",
            "end_year": "2016",
            "url": "https://www.km77.com/coches/volkswagen/passat/2015/berlina/sport/passat-20-tdi-scr-bmt-240-cv-4motion-dsg7/datos",
            "price": "45.165",
            "potencia": "239",
            "consumo": "5,3",
            "longitud": "4.767",
            "maletero": "586",
            "specs": [
                {},
                {},
                {},
                {},
                {},
                {},
                {},
                {},
                {},
                {},
                {},
                {},
                {},
                {},
                {}
            ]
        }
    ]
}