{
    "búsqueda": {
        "marca": "Mercedes-Benz",
        "modelo": "Clase V",
        "version": "V 220 d Extralargo",
        "año mínimo": 2019,
        "año máximo": 2024,
        "km mínimo": 2007,
        "km máximo": 300000,
        "precio mínimo": 1,
        "precio máximo": 9000000,
        "ubicación": {
            "latitud": 40.578494,
            "longitud": -3.892771
        },
        "tipos de cambio": "automatic",
        "tipos de motor": "gasoil",
        "potencia máxima": 163,
        "potencia mínima": 1,
        "categoría": "otros, furgoneta, 4X4, mini furgoneta, coche pequeño, coupé cabrio, sedán, coche familiar",
        "url": "https://es.wallapop.com/app/search?engine=gasoil&min_horse_power=1&max_horse_power=163&min_year=2019&max_year=2024&min_km=2007&max_km=300000&min_sale_price=1&max_sale_price=9000000&gearbox=automatic&brand=Mercedes-Benz&model=Clase V&filters_source=default_filters&keywords=&category_ids=100&longitude=-3.892771&latitude=40.578494&order_by=price_high_to_low"
    },
    "anuncios": [
        {
            "titulo": "Mercedes-Benz Clase V 2019",
            "enlace": "https://es.wallapop.com/item/mercedes-benz-clase-v-2019-1091792088",
            "descripcion": "En perfecto estado",
            "combustible": "Diésel",
            "cambio": "Automático",
            "potencia": "163 cv",
            "año": "2019",
            "kilómetros": "124000 km",
            "precio": 124000.0
        },
        {
            "titulo": "MERCEDES-BENZ V220d 🟢 163cv 9Gtronic EXTRALARGA ",
            "enlace": "https://es.wallapop.com/item/mercedes-benz-v220d-163cv-9gtronic-extralarga-2023-1087509129",
            "descripcion": "PREPARADA PARA DISFRUTARLA, CON UNA CONFIGURACION MAS QUE BUSCADA Y FULL EXTRAS MERCEDES-BENZ V220d 163cv 9Gtronic MODELO AVANT-GARDE EXTRALARGO 8 PLAZAS AÑO 2023 48000km UNIDAD NACIONAL GUÍAS COMPLETAS PARA TOTAL MOBILIDAD INTERIOR ETIQUETA 🟢 LLANTAS ALUMINIO CUERO NEGRO COMPLETO CÁMARAS RADAR ABSOLUTAMENTE PERFECTA DE MECANICA IVA DEDUCIBLE TODO EL LISTADO COMPLETO DE EXTRAS DISPONIBLE PARA VERIFICAR POR EL COMPRADOR 66890€",
            "combustible": "Diésel",
            "cambio": "Automático",
            "potencia": "163 cv",
            "año": "2023",
            "kilómetros": "48000 km",
            "precio": 66890.0
        },
        {
            "titulo": "Mercedes-Benz Clase V 2021",
            "enlace": "https://es.wallapop.com/item/mercedes-benz-clase-v-2021-1020620511",
            "descripcion": "mercedes clase v marco polo 220d del 2021. Furgoneta Camper con espacio para viajar 4 personas cómodamente. Muchos extras, garantía mercedes, todas las revisiones en la casa oficial. Más información por mensaje. Todo original y en perfecto estado. Mejor ver y probar. Precio algo negociable, la transferencia iría a coste del comprador.",
            "combustible": "Diésel",
            "cambio": "Automático",
            "potencia": "163 cv",
            "año": "2021",
            "kilómetros": "45000 km",
            "precio": 66000.0
        },
        {
            "titulo": "Mercedes-Benz Clase V 2023",
            "enlace": "https://es.wallapop.com/item/mercedes-benz-clase-v-2023-1081843092",
            "descripcion": "GLP instalado, 8 plaza, puertas y portón automático, mantenimiento al día, IVA incluido, 622712702",
            "combustible": "Diésel",
            "cambio": "Automático",
            "potencia": "163 cv",
            "año": "2023",
            "kilómetros": "111000 km",
            "precio": 65500.0
        },
        {
            "titulo": "Mercedes-Benz Clase V 2019",
            "enlace": "https://es.wallapop.com/item/mercedes-benz-clase-v-2019-1001300916",
            "descripcion": "Mercedes Marco polo clase V 220 7g-tronic automática en perfecto estado. - Cámara 360 - Faros inteligentes led. - Iluminación interior led. - Calefacción estacionaria con kit de altura. - Llantas de 18\" originales Mercedes. - Fundas de cuero específicas aguirrezabal. - Enganche de remolque - HOMOLOGADA e instalación para 6 plazas - Varios extras más. Plan de mantenimiento mercedes que incluye la próxima revisión, todas las revisiones hechas en concesionario. Muy cuidada. NO ACEPTO CAMBIOS",
            "combustible": "Diésel",
            "cambio": "Automático",
            "potencia": "163 cv",
            "año": "2019",
            "kilómetros": "56000 km",
            "precio": 64500.0
        },
        {
            "titulo": "Mercedes-Benz Clase V 2022",
            "enlace": "https://es.wallapop.com/item/mercedes-benz-clase-v-2022-1058977819",
            "descripcion": "Espectacular V220d Avantgarde 9G-Tronic 8 plazas.Vehiculo nacional con dos revisiones mecanicas gratuitas:Equipada con Butacas en cuero.Paquete integracion smartphone.apple carplay y android auto.sistema multimedia MBUX Mid.Retrovisores electicos y retractiles.Camara de marcha atras.llantas de alecion 17”diseno 5 radio.doble puerta corrediza.luna trasero apertura independiente Cristales tintados.Sensores de luces y lluvia.luz diurna led.Volante multifuncional con levas.Faros led intelligent Ligtht System.etc..",
            "combustible": "Diésel",
            "cambio": "Automático",
            "potencia": "163 cv",
            "año": "2022",
            "kilómetros": "45000 km",
            "precio": 62000.0
        },
        {
            "titulo": "Mercedes-Benz Clase V V 220 d Marco Polo Largo 120 kW (163 CV)",
            "enlace": "https://es.wallapop.com/item/mercedes-benz-clase-v-v-220-d-marco-polo-largo-120-kw-163-cv-1064957650",
            "descripcion": "Precio oferta sujeto a financiación: 61809 EUR. Precio al contado: 67990 EUR. *BIL* GRAN LIQUIDACIÓN FINAL DE AÑO EN OCASIONPLUS REVENTAMOS LOS PRECIOS SÓLO HASTA EL 28 DE DICIEMBRE OCASIONPLUS - 10000 COCHES - 100 CENTROS OCASIONPLUS Nº1 CALIDAD - PRECIO Elige el coche que te guste y te lo llevamos a tu ciudad sólo con reservarlo 15 DÍAS / 1000 KMS DE PRUEBA Hasta 8181€ de descuento en este coche Precio oferta financiado: 61809€ (consulta condiciones específicas de promo - sujeta a aprobación de la entidad financiera) Precio al contado: 67990€ ADEMÁS, HACEMOS LAS MEJORES FINANCIACIONES DEL MERCADO, PREGÚNTANOS!! Equipamiento destacado: Navegador, Car Play, Start/Stop automático, Cámara de marcha atrás, Ayuda aparcamiento, Encendido automático de faros, Faros delanteros led, Asistente de pre-colisión frontal, Control de velocidad, Limitador de velocidad, Volante multifunción, Aire Acondicionado, Freno de estacionamiento eléctrico, Bluetooth, Isofix, Llantas de aleación (17\"). - Coche Nacional. - Garantía total 1 año, con cobertura nacional, ampliable a 24 meses. - Certificado de Kilómetros y ausencia de golpes estructurales. - Sobrevaloramos tu coche en operaciones de cambio. Tásalo ahora en ocasionplus.com - Entregamos cualquier coche en cualquier centro - Abierto Domingo y Festivos.",
            "combustible": "Diésel",
            "cambio": "Automático",
            "potencia": "163 cv",
            "año": "2021",
            "kilómetros": "47027 km",
            "precio": 61809.0
        },
        {
            "titulo": "Mercedes-Benz Clase V 2019",
            "enlace": "https://es.wallapop.com/item/mercedes-benz-clase-v-2019-1077333005",
            "descripcion": "Espectacular unidad!! cuidada al detalle y con un año de garantía!! ubicada en Barcelona y con la posibilidad de entregar en toda España!! nuestro servicio de tramitación totalmente online con firma digital te permite comprar desde tu casa con la tranquilidad y el respaldo total de nuestra empresa. Disponemos de tienda física en Barcelona con taller. Ofrecemos un servicio de garantía de 1 año firmado y con una red de talleres en toda España. SOLICITA UN VIDEO PARA PODER APRECIAR TODOS LOS DETALLES!!! •Perfecto estado de conservación •Todo lo que lleva es de serie, homologado en ficha técnica •Porta bicis original de Mercedes •Nevera •Agua y ducha •Control de crucero •Navegador •Toldo y set de camping •Asientos giratorios •Calefacción estacionaria •Asiento trasero eléctrico •Colchón inflable •Climatizador Bizona El anuncio se muestra a titulo informativo, puede contener errores. Cambio de titularidad a parte 190€",
            "combustible": "Diésel",
            "cambio": "Automático",
            "potencia": "163 cv",
            "año": "2019",
            "kilómetros": "100000 km",
            "precio": 59490.0
        },
        {
            "titulo": "Mercedes-Benz Clase V 220CDI largo",
            "enlace": "https://es.wallapop.com/item/mercedes-benz-clase-v-220cdi-largo-1036215036",
            "descripcion": "Espectacular Clase V 220cdi Largo con 7 plazas, cambio automatico 9G-Tronic, camara trasera, asientos delanteros calefactados, llantas de aleacion de 17”, faros full leds, etc",
            "combustible": "Diésel",
            "cambio": "Automático",
            "potencia": "163 cv",
            "año": "2022",
            "kilómetros": "25570 km",
            "precio": 59290.0
        },
        {
            "titulo": "Mercedes-Benz Clase V 2022",
            "enlace": "https://es.wallapop.com/item/mercedes-benz-clase-v-2022-1080470464",
            "descripcion": "clase V con paquete AMG en perfectas condiciones. Precio 58.800 mas iva. el precio incluye garantia de 12 meses",
            "combustible": "Diésel",
            "cambio": "Automático",
            "potencia": "163 cv",
            "año": "2022",
            "kilómetros": "29000 km",
            "precio": 58800.0
        },
        {
            "titulo": "Mercedes-Benz Clase V 2020",
            "enlace": "https://es.wallapop.com/item/mercedes-benz-clase-v-2020-1037088321",
            "descripcion": "Mercedes Clase V 220 d Compacto Pack AMG Año 2020. 77.000 kms IVA Deducible Un solo propietario Homologado para 7 plazas Pack AMG Puertas correderas eléctricas Porton trasero eléctrico Volante de cuero multifunción Luna abatible Asientos calefactables Cambio automático 9G Faros Led Inteligentes Cristales oscuros Espejos plegables Control de carril Control de velocidad Sensores de parking delanteros y traseros Cámara trasera Ventanillas traseras eléctricas Climatización plazas traseras Navegador 1 año garantía europea Posibilidad de financiación Se entrega totalmente revisada Precio final con IVA incluido.",
            "combustible": "Diésel",
            "cambio": "Automático",
            "potencia": "163 cv",
            "año": "2020",
            "kilómetros": "77000 km",
            "precio": 56990.0
        },
        {
            "titulo": "MERCEDES-BENZ Clase V 220 d Exclusive Largo",
            "enlace": "https://es.wallapop.com/item/mercedes-benz-clase-v-220-d-exclusive-largo-1040497026",
            "descripcion": "A la venta Mercedes Clase V nacional y muy bien equipada: Versión larga, 7 plazas, asientos giratorios, cámara trasera, asientos calefactados, navegador grande, cristales tintados... 12 meses de garantía. para mas información llámenos y le atenderemos sin compromiso. disponemos de más de 150 vehículos en stock a su disposición. precio final sin obligación de financiación. abierto 365 días, no cerramos al mediodía. los vehículos que se muestran en este buscador pueden no corresponder con el modelo publicitado, la información aquí contenida no es legalmente vinculante y no constituye una oferta de venta y firme. coche de segunda mano a la venta. Benidorm altea Alfaz Albir Nucia alicante.",
            "combustible": "Diésel",
            "cambio": "Automático",
            "potencia": "163 cv",
            "año": "2021",
            "kilómetros": "50000 km",
            "precio": 54990.0
        },
        {
            "titulo": "Mercedes-Benz Clase V V 220 d Largo 120 kW (163 CV)",
            "enlace": "https://es.wallapop.com/item/mercedes-benz-clase-v-v-220-d-largo-120-kw-163-cv-1074419131",
            "descripcion": "Ejemplo no vinculante de financiación. PVP: 53.975,00€. Importe financiado: 26.988,00€ con una entrada de 26.987,00€. Plazo 84 cuotas de 465,58€. Comisión de apertura 3,95%, 1.066,03€ financiada. TIN 9,99%, TAE 11,87%. Importe total a devolver: 39.108,72€. Intereses totales: 11.054,69€. Coste total del crédito: 12.120,72€. Financiación ofrecida por las entidades colaboradoras y sujeta a sus criterios de concesión y riesgo. Revise en el contrato de financiación los términos detallados. Ref. U57_22027 Lo más destacado: - Pintura: Azul Cavansita metalizado Pinura metalizada - Tapizado: Tela Santos negro - Asistente de frenado activo - Función HOLD - Navegador - Navigation Plus - Actualización de Mapas 3 años - Live Traffic Information - Paquete aparcamiento - PARKTRONIC - Retrovisores ext. Plegables automáticamente - Consola central con tapa de tipo persiana - Paquete de retrovisores - Cámara de marcha atrás - 9G-TRONIC - Asiento calefactado para acompañante - Asiento calefactado conductor - Tempmatik/climatizador zona de pasajeros - Filtro combustible con separador de agua - LED Intelligent Light System - Piloto trasero, luz de freno e intermitentes LED - Asistente para luz de carretera PLUS - Llantas de aleación de 5 radios dobles 7,0Jx17 - Neumáticos 225/55 R17 - Rueda de repuesto con gato - Asiento de confort para acompañante - Apoyo lumbar en asiento acompañante - Apoyo lumbar en asiento conductor - Puerta corrediza izquierda - Banco de 3-plazas confort 2a fila - Kit fumador - Cristales tintados negros en el compartimento - Vent. portón/puerta trasera con limpia/lavaluneta - Volante En Cuero - Volante Multifunción con Ordenador de Viaje - Ayuda al Arranque en Pendientes - Caja de Enchufe de 12 V en Portaequipajes/Espacio de Carga - Sistema de Llamada de Emergencia Mercedes-Benz - Retrovisor Interior Y Exterior Con Antideslumbramiento Automático - Control Presión Neumáticos Otros puntos destacables: Si es particular se deberá liquidar el IMPUESTO DE MATRICULACIÓN q",
            "combustible": "Diésel",
            "cambio": "Automático",
            "potencia": "163 cv",
            "año": "2022",
            "kilómetros": "45382 km",
            "precio": 54975.0
        },
        {
            "titulo": "Mercedes-Benz Clase V 2019",
            "enlace": "https://es.wallapop.com/item/mercedes-benz-clase-v-2019-1073711980",
            "descripcion": "",
            "combustible": "Diésel",
            "cambio": "Automático",
            "potencia": "163 cv",
            "año": "2019",
            "kilómetros": "135000 km",
            "precio": 54500.0
        },
        {
            "titulo": "Mercedes-Benz Clase V 2019",
            "enlace": "https://es.wallapop.com/item/mercedes-benz-clase-v-2019-1087357092",
            "descripcion": "Mercedes Marcopolo v220. Automático. Techo elevable electrico, asientos traseros eléctricos, camperizada por wesfalia, todo homologado en documentación, toldo lateral, paquete luces led automáticas, pantalla 10\" táctil. Ruedas traseras nuevas, pastillas recién cambiadas. Todos los mantenimiento en casa oficial. Muy bien cuidada.",
            "combustible": "Diésel",
            "cambio": "Automático",
            "potencia": "163 cv",
            "año": "2019",
            "kilómetros": "137000 km",
            "precio": 54500.0
        },
        {
            "titulo": "Mercedes-Benz Clase V Largo 220d 163cv 7 Plazas",
            "enlace": "https://es.wallapop.com/item/mercedes-benz-clase-v-largo-220d-163cv-7-plazas-1055030978",
            "descripcion": "Espectacular unidad de MERCEDES BENZ CLASE V 220D LARGO 163CV 9G-TRONIC!! Nacional En perfecto estado tanto interior como exterior, revisado, navegador, pantalla central Navisson tactil de 10.2\" con conectividad smartphone, pantalla de techo Alpine con conexión Tablet/Teléfono/DVD, auriculares Bluetooth, portabicicletas Mercedes con capacidad para 4 bicicletas, llantas 17\", cristales tintados, asistente de aparcamiento con cámara 360º y muchos más. Precio al contado: 53.900€. Precio financiado: 51.900€. (Financiando al menos 50.000€) Todos nuestros vehículos se entregan transferidos. Este vehículo tiene un año de garantía. Se preparan todos los documentos necesarios para exportación. Pregúntanos por la financiación a tu medida y paga cómodamente. Para recibir una atención adecuada y evitar esperas, llámanos y concreta tu cita. Posibilidad de entrega cualquier punto de España. Los datos del anuncio podrían contener algún error y por tanto no tienen carácter vinculante. Matriculado en 11/2020 Bitcoin accepted here, @auto.gallery #RO CAP #JU PIC #FU #LKY #FAM #3631731",
            "combustible": "Diésel",
            "cambio": "Automático",
            "potencia": "163 cv",
            "año": "2021",
            "kilómetros": "42900 km",
            "precio": 53900.0
        },
        {
            "titulo": "Mercedes-Benz MarcoPolo 220d Largo",
            "enlace": "https://es.wallapop.com/item/mercedes-benz-marcopolo-220d-largo-1093053101",
            "descripcion": "Unico propietario, historial de revisiones en servicio oficial, asiento cama eléctrico, techo elevable con segunda cama, cocina, fregadero, ducha, cámara de marcha atrás, nevera, mesa plegable, asientos delanteros giratorios, faros Led Intelligent Light System, enchufes y todo tipo de tomas de corriente, llanta 17¨, lunas tintadas, cortinas privacidad, sensores de aparcamiento delateros y traseros, reprodución audio SmartPhone Bluetooth, suelo interior simil madera, y un largo etc de cajones/huecos, luces interiores de lectura y posibilidades. Revisada, transferida y con 12 meses de garantia.",
            "combustible": "Diésel",
            "cambio": "Automático",
            "potencia": "163 cv",
            "año": "2019",
            "kilómetros": "116000 km",
            "precio": 51990.0
        },
        {
            "titulo": "Mercedes-Benz Clase V 2021",
            "enlace": "https://es.wallapop.com/item/mercedes-benz-clase-v-2021-1077527345",
            "descripcion": "Vehículo nacional, de un solo propietario y de uso particular, no es taxi. Todas las revisiones hechas en concesionario oficial. Ampliación de garantía con las dos primeras revisiones contratadas (A + B), de las cuales la A a sido realizada y falta por realizar la B (preordenada para el mes de marzo). Acabado Avantgarde que da acceso eléctrico al maletero, con apertura desde la llave y desde el interior del vehículo, y también permite abrir solo el cristal posterior, para cuando no hay suficiente espacio para abrir el portón. Pantalla multimedia con Apple car y android auto.",
            "combustible": "Diésel",
            "cambio": "Automático",
            "potencia": "163 cv",
            "año": "2021",
            "kilómetros": "71000 km",
            "precio": 51500.0
        },
        {
            "titulo": "Mercedes-Benz Clase V 2022",
            "enlace": "https://es.wallapop.com/item/mercedes-benz-clase-v-2022-1074417090",
            "descripcion": "Se vende mercedes clase V 220d del año 2022 con 50000 kms. IVA DEDUCIBLE INCLUIDO EN EL PRECIO. [VZ0] Anclaje de la carga / Orejas de amarre [H16] Asientos en cabina Asiento del conductor calefactable(s) [AHA] Asientos en cabina Asiento del conductor con Soporte lumbar [US5] Asientos en compart. carga: 2ª fila, 3° asiento-banco confort [218] Cámara de marcha atrás [HZ7] Climatizador automático Fondo (Tempomatic) [440] Control de crucero (Tempomat) [KL5] Filtro combustible con Separador de agua [W70] Lunas detrás tintadas / cristal negro [FP3] Paquete espejos [B0MM0] Pintura metalizada [T19] Puerta corredera Compartimento carga/Habitáculo izquierda [P35] Sistema-luz-inteligente",
            "combustible": "Diésel",
            "cambio": "Automático",
            "potencia": "163 cv",
            "año": "2022",
            "kilómetros": "50000 km",
            "precio": 50000.0
        },
        {
            "titulo": "Mercedes-Benz Clase V 2023",
            "enlace": "https://es.wallapop.com/item/mercedes-benz-clase-v-2023-1061763897",
            "descripcion": "PRECIO NEGOCIABLE!! Se vende por cambio de vehiculo y ampliacion de flota. Todos los mantenimientos en Mercedes Oficial. IVA deducible. Km hechos en autopista! Extras: Camara 360 llantas 18 barras techo pantalla 10” 2 puertas laterales alfombrillas goma a medida (tambien originales tela) bombillas philips led (luz corta) luz larga halógena Se vende solo el vehiculo SIN LICENCIA!!",
            "combustible": "Diésel",
            "cambio": "Automático",
            "potencia": "163 cv",
            "año": "2023",
            "kilómetros": "130000 km",
            "precio": 50000.0
        },
        {
            "titulo": "Mercedes-Benz Clase V 2020",
            "enlace": "https://es.wallapop.com/item/mercedes-benz-clase-v-2020-891307140",
            "descripcion": "camperizada, con mueble cama, placa solar, connexión USB, doble bateria y asientos giratorios,nevera,porta bicicleta 4 unitats ,llit dormir COMFORT, 3 ,parts: ample 143 cm, llargada 189 cm, alçada 10 cm PRECIO NO NEGOCIABLE ( Solo particulares)",
            "combustible": "Diésel",
            "cambio": "Automático",
            "potencia": "163 cv",
            "año": "2020",
            "kilómetros": "70869 km",
            "precio": 49990.0
        },
        {
            "titulo": "Mercedes-Benz Clase V220 Larga",
            "enlace": "https://es.wallapop.com/item/mercedes-benz-clase-v220-larga-1091590518",
            "descripcion": "Clase V220d Avantgarde larga automática con 2 años y medio perfectamente mantenida en revisiones y con neumáticos nuevos. Clima trasero, negra metalizada,piel beige natural ,suspensión adaptativa,llanta 18\",cámara trasera,sensores parking,faros led inteligentes,Mbux,barras techo,cristales tintados, Iva deducible, cambio de nombre y 1 año garantía incluidos.",
            "combustible": "Diésel",
            "cambio": "Automático",
            "potencia": "163 cv",
            "año": "2022",
            "kilómetros": "98500 km",
            "precio": 49900.0
        },
        {
            "titulo": "Mercedes-Benz Clase V V 220 d Avantgarde Largo",
            "enlace": "https://es.wallapop.com/item/mercedes-benz-clase-v-v-220-d-avantgarde-largo-1048056461",
            "descripcion": "¡¡¡ Impresionante MERCEDES-BENZ Clase V 220 d Avantgarde Largo !!! IVA deducible. Muy equipado Pantalla táctil. 7 plazas. Ruedas en 17''. Apple Carplay. ... Seleccionamos los mejores vehículos para nuestros clientes??. Muy equipado. Se envían más fotos y videos por WhatsApp, y si quieres verlo en video llamada concertamos cita para que lo vea con detalle. Kilómetros certificados y libre de accidentes. Coches completamente revisados Y GARANTIZADOS 12 MESES ampliables a 24m. Financiación a su medida con o sin entrada y entrega a domicilio en todo el país (consultar condiciones). Revisión y mantenimiento pre-entrega. Aceptamos tu coche usado como parte de pago de menor o mayor valor, máxima. Mas vehículos en perfil Atendemos WhatsApp Llamar antes de acudir a la tienda ya que se atiende con cita previa.",
            "combustible": "Diésel",
            "cambio": "Automático",
            "potencia": "163 cv",
            "año": "2021",
            "kilómetros": "66992 km",
            "precio": 49900.0
        },
        {
            "titulo": "Mercedes-Benz V220d",
            "enlace": "https://es.wallapop.com/item/mercedes-benz-v220d-1057123095",
            "descripcion": "MERCEDES-BENZ V220D 163CV - 08/2022 - 37.000 KMS - Color exterior: Blanco (Blanco Polar). - Acabado interior: Tela negra/gris. - Cambio automático 7G-Tronic. - Sistema de navegación. - Versión de 8 plazas. - Paquete de aparcamiento con cámara trasera. - Paquete de iluminación ambiental. - Asientos delanteros con calefacción. - Asistente para mantenimiento de carril. - Privacidad para plazas traseras. - Llantas de 17\", con diseño en negro brillo/aluminio. - Ventanas abatibles eléctricas traseras. - Control de velocidad. - Climatizador bi-zona. - 2 llaves. - IVA deducible. - Matrícula española. - Historial de mantenimiento en casa oficial. - Libros originales Mercedes-Benz.",
            "combustible": "Diésel",
            "cambio": "Automático",
            "potencia": "163 cv",
            "año": "2022",
            "kilómetros": "37000 km",
            "precio": 49900.0
        },
        {
            "titulo": "Mercedes-Benz Clase V 2022",
            "enlace": "https://es.wallapop.com/item/mercedes-benz-clase-v-2022-1093625827",
            "descripcion": "",
            "combustible": "Diésel",
            "cambio": "Automático",
            "potencia": "163 cv",
            "año": "2022",
            "kilómetros": "54000 km",
            "precio": 48600.0
        },
        {
            "titulo": "Mercedes-Benz Clase V 2022",
            "enlace": "https://es.wallapop.com/item/mercedes-benz-clase-v-2022-1069312108",
            "descripcion": "Vendo Clase V 220d larga automática de 7 plazas con 34.500 kms certificados. Doble puerta lateral aíre acondicionado en la zona trasera, sensores de aparcamiento, volante multifunción, tempomat, impecable y con 24 meses de garantía. Precio financiandola. Consulta condiciones. Hay que añadir al precio el IVA que sería deducible y el impuesto de matriculación en caso de ser particular.",
            "combustible": "Diésel",
            "cambio": "Automático",
            "potencia": "163 cv",
            "año": "2022",
            "kilómetros": "34500 km",
            "precio": 48500.0
        },
        {
            "titulo": "Mercedes-Benz Clase V 2021",
            "enlace": "https://es.wallapop.com/item/mercedes-benz-clase-v-2021-1070268655",
            "descripcion": "Clase V 220 d 6T Largo",
            "combustible": "Diésel",
            "cambio": "Automático",
            "potencia": "163 cv",
            "año": "2021",
            "kilómetros": "75000 km",
            "precio": 48000.0
        },
        {
            "titulo": "Mercedes-Benz Clase V 220 d Largo 120 kW (163 CV)",
            "enlace": "https://es.wallapop.com/item/mercedes-benz-clase-v-220-d-largo-120-kw-163-cv-1069079975",
            "descripcion": "Precio oferta sujeto a financiación: 47718 EUR. Precio al contado: 52490 EUR. *ELX* GRAN LIQUIDACIÓN FINAL DE AÑO EN OCASIONPLUS REVENTAMOS LOS PRECIOS SÓLO HASTA EL 28 DE DICIEMBRE OCASIONPLUS - 10000 COCHES - 100 CENTROS OCASIONPLUS Nº1 CALIDAD - PRECIO Elige el coche que te guste y te lo llevamos a tu ciudad sólo con reservarlo 15 DÍAS / 1000 KMS DE PRUEBA Hasta 4772€ de descuento en este coche Precio oferta financiado: 47718€ (consulta condiciones específicas de promo - sujeta a aprobación de la entidad financiera) Precio al contado: 52490€ ADEMÁS, HACEMOS LAS MEJORES FINANCIACIONES DEL MERCADO, PREGÚNTANOS!! Equipamiento destacado: Tercera fila de asientos, Navegador, Cámara de marcha atrás, Encendido automático de faros, Faros delanteros led, Faros traseros led, Start/Stop automático, Control de velocidad, Limitador de velocidad, Volante multifunción, Aire Acondicionado, Isofix, Bluetooth, Freno de estacionamiento eléctrico, Llantas de aleación (17\"). - Coche Nacional, IVA deducible. - Garantía total 1 año, con cobertura nacional, ampliable a 24 meses. - Certificado de Kilómetros y ausencia de golpes estructurales. - Sobrevaloramos tu coche en operaciones de cambio. Tásalo ahora en ocasionplus.com - Entregamos cualquier coche en cualquier centro - Abierto Domingo y Festivos.",
            "combustible": "Diésel",
            "cambio": "Automático",
            "potencia": "163 cv",
            "año": "2022",
            "kilómetros": "48675 km",
            "precio": 47718.0
        },
        {
            "titulo": "Mercedes-Benz Clase V 220 d Largo 120 kW (163 CV)",
            "enlace": "https://es.wallapop.com/item/mercedes-benz-clase-v-220-d-largo-120-kw-163-cv-1069746205",
            "descripcion": "Precio oferta sujeto a financiación: 47718 EUR. Precio al contado: 52490 EUR. *ELX* GRAN LIQUIDACIÓN FINAL DE AÑO EN OCASIONPLUS REVENTAMOS LOS PRECIOS SÓLO HASTA EL 28 DE DICIEMBRE OCASIONPLUS - 10000 COCHES - 100 CENTROS OCASIONPLUS Nº1 CALIDAD - PRECIO Elige el coche que te guste y te lo llevamos a tu ciudad sólo con reservarlo 15 DÍAS / 1000 KMS DE PRUEBA Hasta 4772€ de descuento en este coche Precio oferta financiado: 47718€ (consulta condiciones específicas de promo - sujeta a aprobación de la entidad financiera) Precio al contado: 52490€ ADEMÁS, HACEMOS LAS MEJORES FINANCIACIONES DEL MERCADO, PREGÚNTANOS!! Equipamiento destacado: Tercera fila de asientos, Navegador, Cámara de marcha atrás, Encendido automático de faros, Faros delanteros led, Faros traseros led, Start/Stop automático, Control de velocidad, Limitador de velocidad, Volante multifunción, Aire Acondicionado, Isofix, Bluetooth, Freno de estacionamiento eléctrico, Llantas de aleación (17\"). - Coche Nacional, IVA deducible. - Garantía total 1 año, con cobertura nacional, ampliable a 24 meses. - Certificado de Kilómetros y ausencia de golpes estructurales. - Sobrevaloramos tu coche en operaciones de cambio. Tásalo ahora en ocasionplus.com - Entregamos cualquier coche en cualquier centro - Abierto Domingo y Festivos.",
            "combustible": "Diésel",
            "cambio": "Automático",
            "potencia": "163 cv",
            "año": "2022",
            "kilómetros": "48675 km",
            "precio": 47718.0
        },
        {
            "titulo": "Mercedes-Benz Clase V 220 d Largo 120 kW (163 CV)",
            "enlace": "https://es.wallapop.com/item/mercedes-benz-clase-v-220-d-largo-120-kw-163-cv-1069744318",
            "descripcion": "Precio oferta sujeto a financiación: 47718 EUR. Precio al contado: 52490 EUR. *ELX* GRAN LIQUIDACIÓN FINAL DE AÑO EN OCASIONPLUS REVENTAMOS LOS PRECIOS SÓLO HASTA EL 28 DE DICIEMBRE OCASIONPLUS - 10000 COCHES - 100 CENTROS OCASIONPLUS Nº1 CALIDAD - PRECIO Elige el coche que te guste y te lo llevamos a tu ciudad sólo con reservarlo 15 DÍAS / 1000 KMS DE PRUEBA Hasta 4772€ de descuento en este coche Precio oferta financiado: 47718€ (consulta condiciones específicas de promo - sujeta a aprobación de la entidad financiera) Precio al contado: 52490€ ADEMÁS, HACEMOS LAS MEJORES FINANCIACIONES DEL MERCADO, PREGÚNTANOS!! Equipamiento destacado: Tercera fila de asientos, Navegador, Cámara de marcha atrás, Encendido automático de faros, Faros delanteros led, Faros traseros led, Start/Stop automático, Control de velocidad, Limitador de velocidad, Volante multifunción, Aire Acondicionado, Isofix, Bluetooth, Freno de estacionamiento eléctrico, Llantas de aleación (17\"). - Coche Nacional, IVA deducible. - Garantía total 1 año, con cobertura nacional, ampliable a 24 meses. - Certificado de Kilómetros y ausencia de golpes estructurales. - Sobrevaloramos tu coche en operaciones de cambio. Tásalo ahora en ocasionplus.com - Entregamos cualquier coche en cualquier centro - Abierto Domingo y Festivos.",
            "combustible": "Diésel",
            "cambio": "Automático",
            "potencia": "163 cv",
            "año": "2022",
            "kilómetros": "48675 km",
            "precio": 47718.0
        },
        {
            "titulo": "Mercedes-Benz Clase V 220 d Largo 120 kW (163 CV)",
            "enlace": "https://es.wallapop.com/item/mercedes-benz-clase-v-220-d-largo-120-kw-163-cv-1069420078",
            "descripcion": "Precio oferta sujeto a financiación: 47718 EUR. Precio al contado: 52490 EUR. *ELX* GRAN LIQUIDACIÓN FINAL DE AÑO EN OCASIONPLUS REVENTAMOS LOS PRECIOS SÓLO HASTA EL 28 DE DICIEMBRE OCASIONPLUS - 10000 COCHES - 100 CENTROS OCASIONPLUS Nº1 CALIDAD - PRECIO Elige el coche que te guste y te lo llevamos a tu ciudad sólo con reservarlo 15 DÍAS / 1000 KMS DE PRUEBA Hasta 4772€ de descuento en este coche Precio oferta financiado: 47718€ (consulta condiciones específicas de promo - sujeta a aprobación de la entidad financiera) Precio al contado: 52490€ ADEMÁS, HACEMOS LAS MEJORES FINANCIACIONES DEL MERCADO, PREGÚNTANOS!! Equipamiento destacado: Tercera fila de asientos, Navegador, Cámara de marcha atrás, Encendido automático de faros, Faros delanteros led, Faros traseros led, Start/Stop automático, Control de velocidad, Limitador de velocidad, Volante multifunción, Aire Acondicionado, Isofix, Bluetooth, Freno de estacionamiento eléctrico, Llantas de aleación (17\"). - Coche Nacional, IVA deducible. - Garantía total 1 año, con cobertura nacional, ampliable a 24 meses. - Certificado de Kilómetros y ausencia de golpes estructurales. - Sobrevaloramos tu coche en operaciones de cambio. Tásalo ahora en ocasionplus.com - Entregamos cualquier coche en cualquier centro - Abierto Domingo y Festivos.",
            "combustible": "Diésel",
            "cambio": "Automático",
            "potencia": "163 cv",
            "año": "2022",
            "kilómetros": "48675 km",
            "precio": 47718.0
        },
        {
            "titulo": "Mercedes-Benz Clase V 220 d Largo 120 kW (163 CV)",
            "enlace": "https://es.wallapop.com/item/mercedes-benz-clase-v-220-d-largo-120-kw-163-cv-1069420937",
            "descripcion": "Precio oferta sujeto a financiación: 47718 EUR. Precio al contado: 52490 EUR. *ELX* GRAN LIQUIDACIÓN FINAL DE AÑO EN OCASIONPLUS REVENTAMOS LOS PRECIOS SÓLO HASTA EL 28 DE DICIEMBRE OCASIONPLUS - 10000 COCHES - 100 CENTROS OCASIONPLUS Nº1 CALIDAD - PRECIO Elige el coche que te guste y te lo llevamos a tu ciudad sólo con reservarlo 15 DÍAS / 1000 KMS DE PRUEBA Hasta 4772€ de descuento en este coche Precio oferta financiado: 47718€ (consulta condiciones específicas de promo - sujeta a aprobación de la entidad financiera) Precio al contado: 52490€ ADEMÁS, HACEMOS LAS MEJORES FINANCIACIONES DEL MERCADO, PREGÚNTANOS!! Equipamiento destacado: Tercera fila de asientos, Navegador, Cámara de marcha atrás, Encendido automático de faros, Faros delanteros led, Faros traseros led, Start/Stop automático, Control de velocidad, Limitador de velocidad, Volante multifunción, Aire Acondicionado, Isofix, Bluetooth, Freno de estacionamiento eléctrico, Llantas de aleación (17\"). - Coche Nacional, IVA deducible. - Garantía total 1 año, con cobertura nacional, ampliable a 24 meses. - Certificado de Kilómetros y ausencia de golpes estructurales. - Sobrevaloramos tu coche en operaciones de cambio. Tásalo ahora en ocasionplus.com - Entregamos cualquier coche en cualquier centro - Abierto Domingo y Festivos.",
            "combustible": "Diésel",
            "cambio": "Automático",
            "potencia": "163 cv",
            "año": "2022",
            "kilómetros": "48675 km",
            "precio": 47718.0
        },
        {
            "titulo": "Mercedes-Benz Clase V 220 d Largo 120 kW (163 CV)",
            "enlace": "https://es.wallapop.com/item/mercedes-benz-clase-v-220-d-largo-120-kw-163-cv-1069748296",
            "descripcion": "Precio oferta sujeto a financiación: 47718 EUR. Precio al contado: 52490 EUR. *ELX* GRAN LIQUIDACIÓN FINAL DE AÑO EN OCASIONPLUS REVENTAMOS LOS PRECIOS SÓLO HASTA EL 28 DE DICIEMBRE OCASIONPLUS - 10000 COCHES - 100 CENTROS OCASIONPLUS Nº1 CALIDAD - PRECIO Elige el coche que te guste y te lo llevamos a tu ciudad sólo con reservarlo 15 DÍAS / 1000 KMS DE PRUEBA Hasta 4772€ de descuento en este coche Precio oferta financiado: 47718€ (consulta condiciones específicas de promo - sujeta a aprobación de la entidad financiera) Precio al contado: 52490€ ADEMÁS, HACEMOS LAS MEJORES FINANCIACIONES DEL MERCADO, PREGÚNTANOS!! Equipamiento destacado: Tercera fila de asientos, Navegador, Cámara de marcha atrás, Encendido automático de faros, Faros delanteros led, Faros traseros led, Start/Stop automático, Control de velocidad, Limitador de velocidad, Volante multifunción, Aire Acondicionado, Isofix, Bluetooth, Freno de estacionamiento eléctrico, Llantas de aleación (17\"). - Coche Nacional, IVA deducible. - Garantía total 1 año, con cobertura nacional, ampliable a 24 meses. - Certificado de Kilómetros y ausencia de golpes estructurales. - Sobrevaloramos tu coche en operaciones de cambio. Tásalo ahora en ocasionplus.com - Entregamos cualquier coche en cualquier centro - Abierto Domingo y Festivos.",
            "combustible": "Diésel",
            "cambio": "Automático",
            "potencia": "163 cv",
            "año": "2022",
            "kilómetros": "48675 km",
            "precio": 47718.0
        },
        {
            "titulo": "Mercedes-Benz Clase V 220 d Largo 120 kW (163 CV)",
            "enlace": "https://es.wallapop.com/item/mercedes-benz-clase-v-220-d-largo-120-kw-163-cv-1069743524",
            "descripcion": "Precio oferta sujeto a financiación: 47718 EUR. Precio al contado: 52490 EUR. *ELX* GRAN LIQUIDACIÓN FINAL DE AÑO EN OCASIONPLUS REVENTAMOS LOS PRECIOS SÓLO HASTA EL 28 DE DICIEMBRE OCASIONPLUS - 10000 COCHES - 100 CENTROS OCASIONPLUS Nº1 CALIDAD - PRECIO Elige el coche que te guste y te lo llevamos a tu ciudad sólo con reservarlo 15 DÍAS / 1000 KMS DE PRUEBA Hasta 4772€ de descuento en este coche Precio oferta financiado: 47718€ (consulta condiciones específicas de promo - sujeta a aprobación de la entidad financiera) Precio al contado: 52490€ ADEMÁS, HACEMOS LAS MEJORES FINANCIACIONES DEL MERCADO, PREGÚNTANOS!! Equipamiento destacado: Tercera fila de asientos, Navegador, Cámara de marcha atrás, Encendido automático de faros, Faros delanteros led, Faros traseros led, Start/Stop automático, Control de velocidad, Limitador de velocidad, Volante multifunción, Aire Acondicionado, Isofix, Bluetooth, Freno de estacionamiento eléctrico, Llantas de aleación (17\"). - Coche Nacional, IVA deducible. - Garantía total 1 año, con cobertura nacional, ampliable a 24 meses. - Certificado de Kilómetros y ausencia de golpes estructurales. - Sobrevaloramos tu coche en operaciones de cambio. Tásalo ahora en ocasionplus.com - Entregamos cualquier coche en cualquier centro - Abierto Domingo y Festivos.",
            "combustible": "Diésel",
            "cambio": "Automático",
            "potencia": "163 cv",
            "año": "2022",
            "kilómetros": "48675 km",
            "precio": 47718.0
        },
        {
            "titulo": "Mercedes-Benz Clase V 220 d Largo 120 kW (163 CV)",
            "enlace": "https://es.wallapop.com/item/mercedes-benz-clase-v-220-d-largo-120-kw-163-cv-1067423138",
            "descripcion": "Precio oferta sujeto a financiación: 47718 EUR. Precio al contado: 52490 EUR. *ELX* GRAN LIQUIDACIÓN FINAL DE AÑO EN OCASIONPLUS REVENTAMOS LOS PRECIOS SÓLO HASTA EL 28 DE DICIEMBRE OCASIONPLUS - 10000 COCHES - 100 CENTROS OCASIONPLUS Nº1 CALIDAD - PRECIO Elige el coche que te guste y te lo llevamos a tu ciudad sólo con reservarlo 15 DÍAS / 1000 KMS DE PRUEBA Hasta 4772€ de descuento en este coche Precio oferta financiado: 47718€ (consulta condiciones específicas de promo - sujeta a aprobación de la entidad financiera) Precio al contado: 52490€ ADEMÁS, HACEMOS LAS MEJORES FINANCIACIONES DEL MERCADO, PREGÚNTANOS!! Equipamiento destacado: Tercera fila de asientos, Navegador, Cámara de marcha atrás, Encendido automático de faros, Faros delanteros led, Faros traseros led, Start/Stop automático, Control de velocidad, Limitador de velocidad, Volante multifunción, Aire Acondicionado, Isofix, Bluetooth, Freno de estacionamiento eléctrico, Llantas de aleación (17\"). - Coche Nacional, IVA deducible. - Garantía total 1 año, con cobertura nacional, ampliable a 24 meses. - Certificado de Kilómetros y ausencia de golpes estructurales. - Sobrevaloramos tu coche en operaciones de cambio. Tásalo ahora en ocasionplus.com - Entregamos cualquier coche en cualquier centro - Abierto Domingo y Festivos.",
            "combustible": "Diésel",
            "cambio": "Automático",
            "potencia": "163 cv",
            "año": "2022",
            "kilómetros": "48675 km",
            "precio": 47718.0
        },
        {
            "titulo": "Mercedes-Benz Clase V 220 d Largo 120 kW (163 CV)",
            "enlace": "https://es.wallapop.com/item/mercedes-benz-clase-v-220-d-largo-120-kw-163-cv-1069742080",
            "descripcion": "Precio oferta sujeto a financiación: 47718 EUR. Precio al contado: 52490 EUR. *ELX* GRAN LIQUIDACIÓN FINAL DE AÑO EN OCASIONPLUS REVENTAMOS LOS PRECIOS SÓLO HASTA EL 28 DE DICIEMBRE OCASIONPLUS - 10000 COCHES - 100 CENTROS OCASIONPLUS Nº1 CALIDAD - PRECIO Elige el coche que te guste y te lo llevamos a tu ciudad sólo con reservarlo 15 DÍAS / 1000 KMS DE PRUEBA Hasta 4772€ de descuento en este coche Precio oferta financiado: 47718€ (consulta condiciones específicas de promo - sujeta a aprobación de la entidad financiera) Precio al contado: 52490€ ADEMÁS, HACEMOS LAS MEJORES FINANCIACIONES DEL MERCADO, PREGÚNTANOS!! Equipamiento destacado: Tercera fila de asientos, Navegador, Cámara de marcha atrás, Encendido automático de faros, Faros delanteros led, Faros traseros led, Start/Stop automático, Control de velocidad, Limitador de velocidad, Volante multifunción, Aire Acondicionado, Isofix, Bluetooth, Freno de estacionamiento eléctrico, Llantas de aleación (17\"). - Coche Nacional, IVA deducible. - Garantía total 1 año, con cobertura nacional, ampliable a 24 meses. - Certificado de Kilómetros y ausencia de golpes estructurales. - Sobrevaloramos tu coche en operaciones de cambio. Tásalo ahora en ocasionplus.com - Entregamos cualquier coche en cualquier centro - Abierto Domingo y Festivos.",
            "combustible": "Diésel",
            "cambio": "Automático",
            "potencia": "163 cv",
            "año": "2022",
            "kilómetros": "48675 km",
            "precio": 47718.0
        },
        {
            "titulo": "Mercedes-Benz Clase V 220 d Largo 120 kW (163 CV)",
            "enlace": "https://es.wallapop.com/item/mercedes-benz-clase-v-220-d-largo-120-kw-163-cv-1069082293",
            "descripcion": "Precio oferta sujeto a financiación: 47718 EUR. Precio al contado: 52490 EUR. *ELX* GRAN LIQUIDACIÓN FINAL DE AÑO EN OCASIONPLUS REVENTAMOS LOS PRECIOS SÓLO HASTA EL 28 DE DICIEMBRE OCASIONPLUS - 10000 COCHES - 100 CENTROS OCASIONPLUS Nº1 CALIDAD - PRECIO Elige el coche que te guste y te lo llevamos a tu ciudad sólo con reservarlo 15 DÍAS / 1000 KMS DE PRUEBA Hasta 4772€ de descuento en este coche Precio oferta financiado: 47718€ (consulta condiciones específicas de promo - sujeta a aprobación de la entidad financiera) Precio al contado: 52490€ ADEMÁS, HACEMOS LAS MEJORES FINANCIACIONES DEL MERCADO, PREGÚNTANOS!! Equipamiento destacado: Tercera fila de asientos, Navegador, Cámara de marcha atrás, Encendido automático de faros, Faros delanteros led, Faros traseros led, Start/Stop automático, Control de velocidad, Limitador de velocidad, Volante multifunción, Aire Acondicionado, Isofix, Bluetooth, Freno de estacionamiento eléctrico, Llantas de aleación (17\"). - Coche Nacional, IVA deducible. - Garantía total 1 año, con cobertura nacional, ampliable a 24 meses. - Certificado de Kilómetros y ausencia de golpes estructurales. - Sobrevaloramos tu coche en operaciones de cambio. Tásalo ahora en ocasionplus.com - Entregamos cualquier coche en cualquier centro - Abierto Domingo y Festivos.",
            "combustible": "Diésel",
            "cambio": "Automático",
            "potencia": "163 cv",
            "año": "2022",
            "kilómetros": "48675 km",
            "precio": 47718.0
        },
        {
            "titulo": "Mercedes-Benz Clase V 220 d Largo 120 kW (163 CV)",
            "enlace": "https://es.wallapop.com/item/mercedes-benz-clase-v-220-d-largo-120-kw-163-cv-1068079663",
            "descripcion": "Precio oferta sujeto a financiación: 47718 EUR. Precio al contado: 52490 EUR. *ELX* GRAN LIQUIDACIÓN FINAL DE AÑO EN OCASIONPLUS REVENTAMOS LOS PRECIOS SÓLO HASTA EL 28 DE DICIEMBRE OCASIONPLUS - 10000 COCHES - 100 CENTROS OCASIONPLUS Nº1 CALIDAD - PRECIO Elige el coche que te guste y te lo llevamos a tu ciudad sólo con reservarlo 15 DÍAS / 1000 KMS DE PRUEBA Hasta 4772€ de descuento en este coche Precio oferta financiado: 47718€ (consulta condiciones específicas de promo - sujeta a aprobación de la entidad financiera) Precio al contado: 52490€ ADEMÁS, HACEMOS LAS MEJORES FINANCIACIONES DEL MERCADO, PREGÚNTANOS!! Equipamiento destacado: Tercera fila de asientos, Navegador, Cámara de marcha atrás, Encendido automático de faros, Faros delanteros led, Faros traseros led, Start/Stop automático, Control de velocidad, Limitador de velocidad, Volante multifunción, Aire Acondicionado, Isofix, Bluetooth, Freno de estacionamiento eléctrico, Llantas de aleación (17\"). - Coche Nacional, IVA deducible. - Garantía total 1 año, con cobertura nacional, ampliable a 24 meses. - Certificado de Kilómetros y ausencia de golpes estructurales. - Sobrevaloramos tu coche en operaciones de cambio. Tásalo ahora en ocasionplus.com - Entregamos cualquier coche en cualquier centro - Abierto Domingo y Festivos.",
            "combustible": "Diésel",
            "cambio": "Automático",
            "potencia": "163 cv",
            "año": "2022",
            "kilómetros": "48675 km",
            "precio": 47718.0
        },
        {
            "titulo": "Mercedes-Benz Clase V 220 d 2019",
            "enlace": "https://es.wallapop.com/item/mercedes-benz-clase-v-220-d-2019-1085078065",
            "descripcion": "CLASE V 220 d LARGO. Equipado con pintura metalizada azul cavansita, doble puerta corredera, cambio automático 7G-Tronic, llantas aleación 17', volante multifunción, cámara marcha atrás, enganche remolque, cristales tintados, AC pasajeros, luces LED automáticas en carretera. garantía incluida de 2 años con financiación incluido. Joel 654105994",
            "combustible": "Diésel",
            "cambio": "Automático",
            "potencia": "163 cv",
            "año": "2019",
            "kilómetros": "115000 km",
            "precio": 47000.0
        },
        {
            "titulo": "Mercedes-Benz Clase V 2019",
            "enlace": "https://es.wallapop.com/item/mercedes-benz-clase-v-2019-1068877670",
            "descripcion": "LUJO ADAPTADO A MINUSVALIDOS, rampa eléctrica plegable. Motor 220CDI 4matic (Tracción a las 4 ruedas) automática, a penas 20.000 km. Impuestos pagados.",
            "combustible": "Diésel",
            "cambio": "Automático",
            "potencia": "163 cv",
            "año": "2019",
            "kilómetros": "26000 km",
            "precio": 46999.0
        }
    ]
}